<?xml version="1.0" encoding="UTF-8"?>
<cesAna version="1.0.4" xmlns="http://www.xces.org/schema/2003" xmlns:xlink="http://www.w3.org/1999/xlink" xmlns:xsi="http://www.w3.org/2001/XMLSchema-instance" xsi:schemaLocation="http://www.xces.org/schema/2003 http://www.xces.org/schema/2003/xcesAna.xsd">
 <struct from="18" id="n02630468_wf5" to="31" type="auto">
  <feat name="wnsk" value="istiophoridae%1:05:00::"/>
  <feat name="text" value="Istiophoridae"/>
 </struct>
 <struct from="35" id="n02630615_wf2" to="39" type="man">
  <feat name="wnsk" value="kind%1:09:00::"/>
  <feat name="text" value="kind"/>
 </struct>
 <struct from="43" id="n02630615_wf4" to="51" type="man">
  <feat name="wnsk" value="sailfish%1:05:00::"/>
  <feat name="text" value="sailfish"/>
 </struct>
 <struct from="53" id="n02630739_wf1" to="58" type="man">
  <feat name="wnsk" value="giant%3:00:00:large:00"/>
  <feat name="text" value="giant"/>
 </struct>
 <struct from="59" id="n02630739_wf2" to="63" type="man">
  <feat name="wnsk" value="warm%3:00:01::"/>
  <feat name="text" value="warm"/>
 </struct>
 <struct from="64" id="n02630739_wf3" to="69" type="man">
  <feat name="wnsk" value="water%1:17:00::"/>
  <feat name="text" value="water"/>
 </struct>
 <struct from="80" id="n02630739_wf6" to="86" type="un">
  <feat name="text" value="having"/>
 </struct>
 <struct from="89" id="n02630739_wf8" to="98" type="man">
  <feat name="wnsk" value="prolonged%3:00:00:long:01"/>
  <feat name="text" value="prolonged"/>
 </struct>
 <struct from="103" id="n02630739_wf10" to="110" type="man">
  <feat name="wnsk" value="rounded%3:00:00::"/>
  <feat name="text" value="rounded"/>
 </struct>
 <struct from="111" id="n02630739_wf11" to="120" type="man">
  <feat name="wnsk" value="toothless%3:00:00::"/>
  <feat name="text" value="toothless"/>
 </struct>
 <struct from="132" id="n02630926_wf1" to="139" type="auto">
  <feat name="wnsk" value="marlin%1:05:00::"/>
  <feat name="text" value="marlins"/>
 </struct>
 <struct from="141" id="n02631041_wf1" to="146" type="man">
  <feat name="wnsk" value="large%3:00:00::"/>
  <feat name="text" value="large"/>
 </struct>
 <struct from="147" id="n02631041_wf2" to="157" type="man">
  <feat name="wnsk" value="long-jawed%3:00:00:jawed:00"/>
  <feat name="text" value="long-jawed"/>
 </struct>
 <struct from="158" id="n02631041_wf3" to="165" type="un">
  <feat name="text" value="oceanic"/>
 </struct>
 <struct from="180" id="n02631041_wf7" to="187" type="man">
  <feat name="wnsk" value="related%3:00:01::"/>
  <feat name="text" value="related"/>
 </struct>
 <struct from="191" id="n02631041_wf9" to="201" type="man">
  <feat name="wnsk" value="sailfish%1:05:00::"/>
  <feat name="text" value="sailfishes"/>
 </struct>
 <struct from="206" id="n02631041_wf11" to="217" type="man">
  <feat name="wnsk" value="spearfish%1:05:01::"/>
  <feat name="text" value="spearfishes"/>
 </struct>
 <struct from="219" id="n02631041_wf13" to="222" type="auto">
  <feat name="wnsk" value="not%4:02:00::"/>
  <feat name="text" value="not"/>
 </struct>
 <struct from="223" id="n02631041_wf14" to="233" type="un">
  <feat name="text" value="completely"/>
 </struct>
 <struct from="234" id="n02631041_wf15" to="246" type="man">
  <feat name="wnsk" value="cold-blooded%3:00:00::"/>
  <feat name="text" value="cold-blooded"/>
 </struct>
 <struct from="247" id="n02631041_wf16" to="251" type="auto">
  <feat name="wnsk" value="i.e.%4:02:00::"/>
  <feat name="text" value="i.e."/>
 </struct>
 <struct from="252" id="n02631041_wf17" to="256" type="man">
  <feat name="wnsk" value="able%3:00:00:capable:00"/>
  <feat name="text" value="able"/>
 </struct>
 <struct from="260" id="n02631041_wf19" to="264" type="man">
  <feat name="wnsk" value="warm%2:30:01::"/>
  <feat name="wnsk" value="warm%2:30:00::"/>
  <feat name="text" value="warm"/>
 </struct>
 <struct from="271" id="n02631041_wf21" to="277" type="man">
  <feat name="wnsk" value="brain%1:08:00::"/>
  <feat name="text" value="brains"/>
 </struct>
 <struct from="282" id="n02631041_wf23" to="286" type="man">
  <feat name="wnsk" value="eye%1:08:00::"/>
  <feat name="text" value="eyes"/>
 </struct>
 <struct from="288" id="n02631330_wf1" to="295" type="man">
  <feat name="wnsk" value="large%3:00:00::"/>
  <feat name="text" value="largest"/>
 </struct>
 <struct from="296" id="n02631330_wf2" to="302" type="auto">
  <feat name="wnsk" value="marlin%1:05:00::"/>
  <feat name="text" value="marlin"/>
 </struct>
 <struct from="304" id="n02631330_wf4" to="307" type="un">
  <feat name="text" value="may"/>
 </struct>
 <struct from="308" id="n02631330_wf5" to="313" type="man">
  <feat name="wnsk" value="reach%2:38:00::"/>
  <feat name="text" value="reach"/>
 </struct>
 <struct from="319" id="n02631330_wf7" to="325" type="man">
  <feat name="wnsk" value="pound%1:23:09::"/>
  <feat name="text" value="pounds"/>
 </struct>
 <struct from="327" id="n02631330_wf9" to="332" type="un">
  <feat name="text" value="found"/>
 </struct>
 <struct from="333" id="n02631330_wf10" to="342" type="man">
  <feat name="wnsk" value="worldwide%3:00:00:international:00"/>
  <feat name="wnsk" value="worldwide%3:00:00:intercontinental:00"/>
  <feat name="text" value="worldwide"/>
 </struct>
 <struct from="346" id="n02631330_wf12" to="350" type="man">
  <feat name="wnsk" value="warm%3:00:01::"/>
  <feat name="text" value="warm"/>
 </struct>
 <struct from="351" id="n02631330_wf13" to="355" type="man">
  <feat name="wnsk" value="sea%1:17:00::"/>
  <feat name="text" value="seas"/>
 </struct>
 <struct from="357" id="n02631475_wf1" to="362" type="man">
  <feat name="wnsk" value="large%3:00:00::"/>
  <feat name="text" value="large"/>
 </struct>
 <struct from="395" id="n02631475_wf9" to="398" type="un">
  <feat name="text" value="may"/>
 </struct>
 <struct from="399" id="n02631475_wf10" to="404" type="man">
  <feat name="wnsk" value="reach%2:38:00::"/>
  <feat name="text" value="reach"/>
 </struct>
 <struct from="410" id="n02631475_wf12" to="416" type="man">
  <feat name="wnsk" value="pound%1:23:09::"/>
  <feat name="text" value="pounds"/>
 </struct>
 <struct from="418" id="n02631628_wf1" to="425" type="man">
  <feat name="wnsk" value="pacific%3:01:00::"/>
  <feat name="text" value="Pacific"/>
 </struct>
 <struct from="445" id="n02631628_wf6" to="451" type="man">
  <feat name="wnsk" value="marked%3:00:00::"/>
  <feat name="text" value="marked"/>
 </struct>
 <struct from="467" id="n02631628_wf10" to="475" type="un">
  <feat name="text" value="vertical"/>
 </struct>
 <struct from="476" id="n02631628_wf11" to="483" type="man">
  <feat name="wnsk" value="stripe%1:07:00::"/>
  <feat name="text" value="stripes"/>
 </struct>
 <struct from="485" id="n02631775_wf1" to="490" type="man">
  <feat name="wnsk" value="small%3:00:00::"/>
  <feat name="text" value="small"/>
 </struct>
 <struct from="491" id="n02631775_wf2" to="497" type="auto">
  <feat name="wnsk" value="marlin%1:05:00::"/>
  <feat name="text" value="marlin"/>
 </struct>
 <struct from="506" id="n02631775_tok4" to="512" type="un">
  <feat name="text" value="pounds"/>
 </struct>
 <struct from="517" id="n02631775_wf4" to="524" type="man">
  <feat name="wnsk" value="western%3:00:00:west:00"/>
  <feat name="text" value="western"/>
 </struct>
 <struct from="525" id="n02631775_wf5" to="533" type="man">
  <feat name="wnsk" value="atlantic%1:17:00::"/>
  <feat name="text" value="Atlantic"/>
 </struct>
 <struct from="537" id="n02631899_wf2" to="542" type="man">
  <feat name="wnsk" value="genus%1:14:00::"/>
  <feat name="text" value="genus"/>
 </struct>
 <struct from="546" id="n02631899_wf4" to="559" type="auto">
  <feat name="wnsk" value="istiophoridae%1:05:00::"/>
  <feat name="text" value="Istiophoridae"/>
 </struct>
 <struct from="568" id="n02632039_wf3" to="575" type="un">
  <feat name="text" value="several"/>
 </struct>
 <struct from="576" id="n02632039_wf4" to="581" type="man">
  <feat name="wnsk" value="large%3:00:00::"/>
  <feat name="text" value="large"/>
 </struct>
 <struct from="582" id="n02632039_wf5" to="590" type="man">
  <feat name="wnsk" value="vigorous%3:00:00:energetic:00"/>
  <feat name="text" value="vigorous"/>
 </struct>
 <struct from="591" id="n02632039_wf6" to="598" type="auto">
  <feat name="wnsk" value="pelagic%3:01:00::"/>
  <feat name="text" value="pelagic"/>
 </struct>
 <struct from="599" id="n02632039_wf7" to="605" type="man">
  <feat name="wnsk" value="fish%1:05:00::"/>
  <feat name="text" value="fishes"/>
 </struct>
 <struct from="606" id="n02632039_wf8" to="616" type="auto">
  <feat name="wnsk" value="resemble%2:42:00::"/>
  <feat name="text" value="resembling"/>
 </struct>
 <struct from="617" id="n02632039_wf9" to="627" type="man">
  <feat name="wnsk" value="sailfish%1:05:00::"/>
  <feat name="text" value="sailfishes"/>
 </struct>
 <struct from="637" id="n02632039_wf12" to="642" type="un">
  <feat name="text" value="first"/>
 </struct>
 <struct from="654" id="n02632039_wf15" to="658" type="un">
  <feat name="text" value="much"/>
 </struct>
 <struct from="659" id="n02632039_wf16" to="666" type="un">
  <feat name="text" value="reduced"/>
 </struct>
 <struct from="668" id="n02632039_wf18" to="677" type="man">
  <feat name="wnsk" value="worldwide%3:00:00:international:00"/>
  <feat name="wnsk" value="worldwide%3:00:00:intercontinental:00"/>
  <feat name="text" value="worldwide"/>
 </struct>
 <struct from="682" id="n02632039_wf20" to="686" type="un">
  <feat name="text" value="rare"/>
 </struct>
 <struct from="688" id="n02632239_wf1" to="695" type="auto">
  <feat name="wnsk" value="louvar%1:05:00::"/>
  <feat name="text" value="louvars"/>
 </struct>
 <struct from="715" id="n02632359_wf5" to="724" type="auto">
  <feat name="wnsk" value="luvaridae%1:05:00::"/>
  <feat name="text" value="Luvaridae"/>
 </struct>
 <struct from="726" id="n02632494_wf1" to="731" type="man">
  <feat name="wnsk" value="large%3:00:00::"/>
  <feat name="text" value="large"/>
 </struct>
 <struct from="732" id="n02632494_wf2" to="739" type="man">
  <feat name="wnsk" value="silvery%3:00:00:bright:00"/>
  <feat name="text" value="silvery"/>
 </struct>
 <struct from="740" id="n02632494_wf3" to="744" type="man">
  <feat name="wnsk" value="fish%1:05:00::"/>
  <feat name="text" value="fish"/>
 </struct>
 <struct from="745" id="n02632494_wf4" to="750" type="un">
  <feat name="text" value="found"/>
 </struct>
 <struct from="751" id="n02632494_wf5" to="760" type="man">
  <feat name="wnsk" value="worldwide%3:00:00:international:00"/>
  <feat name="wnsk" value="worldwide%3:00:00:intercontinental:00"/>
  <feat name="text" value="worldwide"/>
 </struct>
 <struct from="764" id="n02632494_wf7" to="768" type="man">
  <feat name="wnsk" value="warm%3:00:01::"/>
  <feat name="text" value="warm"/>
 </struct>
 <struct from="769" id="n02632494_wf8" to="773" type="man">
  <feat name="wnsk" value="sea%1:17:00::"/>
  <feat name="text" value="seas"/>
 </struct>
 <struct from="778" id="n02632494_wf10" to="785" type="man">
  <feat name="wnsk" value="nowhere%4:02:00::"/>
  <feat name="text" value="nowhere"/>
 </struct>
 <struct from="786" id="n02632494_wf11" to="792" type="un">
  <feat name="text" value="common"/>
 </struct>
 <struct from="794" id="n02632494_wf13" to="803" type="auto">
  <feat name="wnsk" value="resemble%2:42:00::"/>
  <feat name="text" value="resembles"/>
 </struct>
 <struct from="806" id="n02632494_wf15" to="811" type="man">
  <feat name="wnsk" value="whale%1:05:00::"/>
  <feat name="text" value="whale"/>
 </struct>
 <struct from="816" id="n02632494_wf17" to="821" type="man">
  <feat name="wnsk" value="feed%2:34:00::"/>
  <feat name="text" value="feeds"/>
 </struct>
 <struct from="825" id="n02632494_wf19" to="833" type="auto">
  <feat name="wnsk" value="plankton%1:05:00::"/>
  <feat name="text" value="plankton"/>
 </struct>
 <struct from="835" id="n02632694_wf1" to="847" type="man">
  <feat name="wnsk" value="butterfish%1:05:01::"/>
  <feat name="text" value="butterfishes"/>
 </struct>
 <struct from="880" id="n02632989_wf1" to="885" type="man">
  <feat name="wnsk" value="small%3:00:00::"/>
  <feat name="text" value="small"/>
 </struct>
 <struct from="886" id="n02632989_wf2" to="892" type="man">
  <feat name="wnsk" value="marine%3:00:00:aquatic:00"/>
  <feat name="text" value="marine"/>
 </struct>
 <struct from="893" id="n02632989_wf3" to="897" type="man">
  <feat name="wnsk" value="fish%1:05:00::"/>
  <feat name="text" value="fish"/>
 </struct>
 <struct from="905" id="n02632989_wf6" to="910" type="man">
  <feat name="wnsk" value="short%3:00:01::"/>
  <feat name="text" value="short"/>
 </struct>
 <struct from="911" id="n02632989_wf7" to="921" type="man">
  <feat name="wnsk" value="compressed%3:00:00:thin:01"/>
  <feat name="text" value="compressed"/>
 </struct>
 <struct from="922" id="n02632989_wf8" to="926" type="man">
  <feat name="wnsk" value="body%1:08:01::"/>
  <feat name="text" value="body"/>
 </struct>
 <struct from="931" id="n02632989_wf10" to="937" type="man">
  <feat name="wnsk" value="feeble%3:00:00:frail:00"/>
  <feat name="text" value="feeble"/>
 </struct>
 <struct from="938" id="n02632989_wf11" to="944" type="man">
  <feat name="wnsk" value="spine%1:05:00::"/>
  <feat name="text" value="spines"/>
 </struct>
 <struct from="948" id="n02633287_wf2" to="953" type="man">
  <feat name="wnsk" value="genus%1:14:00::"/>
  <feat name="text" value="genus"/>
 </struct>
 <struct from="957" id="n02633287_wf4" to="969" type="auto">
  <feat name="wnsk" value="stromateidae%1:05:00::"/>
  <feat name="text" value="Stromateidae"/>
 </struct>
 <struct from="971" id="n02633422_wf1" to="976" type="man">
  <feat name="wnsk" value="small%3:00:00::"/>
  <feat name="text" value="small"/>
 </struct>
 <struct from="1008" id="n02633555_wf2" to="1013" type="man">
  <feat name="wnsk" value="genus%1:14:00::"/>
  <feat name="text" value="genus"/>
 </struct>
 <struct from="1017" id="n02633555_wf4" to="1029" type="auto">
  <feat name="wnsk" value="stromateidae%1:05:00::"/>
  <feat name="text" value="Stromateidae"/>
 </struct>
 <struct from="1031" id="n02633677_wf1" to="1038" type="auto">
  <feat name="wnsk" value="smaller%3:00:00:small:00"/>
  <feat name="text" value="smaller"/>
 </struct>
 <struct from="1061" id="n02633677_wf6" to="1067" type="un">
  <feat name="text" value="common"/>
 </struct>
 <struct from="1086" id="n02633844_wf2" to="1091" type="man">
  <feat name="wnsk" value="genus%1:14:00::"/>
  <feat name="text" value="genus"/>
 </struct>
 <struct from="1095" id="n02633844_wf4" to="1107" type="auto">
  <feat name="wnsk" value="stromateidae%1:05:00::"/>
  <feat name="text" value="Stromateidae"/>
 </struct>
 <struct from="1109" id="n02633977_wf1" to="1119" type="man">
  <feat name="wnsk" value="butterfish%1:05:01::"/>
  <feat name="text" value="butterfish"/>
 </struct>
 <struct from="1120" id="n02633977_wf2" to="1122" type="un">
  <feat name="text" value="up"/>
 </struct>
 <struct from="1128" id="n02633977_wf5" to="1132" type="man">
  <feat name="wnsk" value="foot%1:23:00::"/>
  <feat name="text" value="foot"/>
 </struct>
 <struct from="1133" id="n02633977_wf6" to="1137" type="man">
  <feat name="wnsk" value="long%3:00:01::"/>
  <feat name="text" value="long"/>
 </struct>
 <struct from="1141" id="n02633977_wf8" to="1149" type="man">
  <feat name="wnsk" value="atlantic%3:01:00::"/>
  <feat name="text" value="Atlantic"/>
 </struct>
 <struct from="1150" id="n02633977_wf9" to="1156" type="man">
  <feat name="wnsk" value="water%1:17:00::"/>
  <feat name="text" value="waters"/>
 </struct>
 <struct from="1180" id="n02633977_wf14" to="1189" type="man">
  <feat name="wnsk" value="argentina%1:15:00::"/>
  <feat name="text" value="Argentina"/>
 </struct>
 <struct from="1193" id="n02634156_wf2" to="1198" type="man">
  <feat name="wnsk" value="genus%1:14:00::"/>
  <feat name="text" value="genus"/>
 </struct>
 <struct from="1202" id="n02634156_wf4" to="1214" type="auto">
  <feat name="wnsk" value="stromateidae%1:05:00::"/>
  <feat name="text" value="Stromateidae"/>
 </struct>
 <struct from="1216" id="n02634285_wf1" to="1221" type="man">
  <feat name="wnsk" value="small%3:00:00::"/>
  <feat name="text" value="small"/>
 </struct>
 <struct from="1225" id="n02634285_tok3" to="1231" type="un">
  <feat name="text" value="inches"/>
 </struct>
 <struct from="1233" id="n02634285_wf2" to="1241" type="un">
  <feat name="text" value="tropical"/>
 </struct>
 <struct from="1242" id="n02634285_wf3" to="1254" type="man">
  <feat name="wnsk" value="butterfish%1:05:01::"/>
  <feat name="text" value="butterfishes"/>
 </struct>
 <struct from="1255" id="n02634285_wf4" to="1260" type="un">
  <feat name="text" value="found"/>
 </struct>
 <struct from="1261" id="n02634285_wf5" to="1270" type="man">
  <feat name="wnsk" value="worldwide%3:00:00:intercontinental:00"/>
  <feat name="wnsk" value="worldwide%3:00:00:international:00"/>
  <feat name="text" value="worldwide"/>
 </struct>
 <struct from="1274" id="n02634414_wf2" to="1279" type="man">
  <feat name="wnsk" value="genus%1:14:00::"/>
  <feat name="text" value="genus"/>
 </struct>
 <struct from="1283" id="n02634414_wf4" to="1295" type="auto">
  <feat name="wnsk" value="stromateidae%1:05:00::"/>
  <feat name="text" value="Stromateidae"/>
 </struct>
 <struct from="1297" id="n02634545_wf1" to="1303" type="man">
  <feat name="wnsk" value="large%3:00:00::"/>
  <feat name="wnsk" value="larger%3:00:00:large:00"/>
  <feat name="text" value="larger"/>
 </struct>
 <struct from="1304" id="n02634545_wf2" to="1316" type="un">
  <feat name="text" value="butterfishes"/>
 </struct>
 <struct from="1324" id="n02634545_wf5" to="1331" type="un">
  <feat name="text" value="western"/>
 </struct>
 <struct from="1332" id="n02634545_wf6" to="1340" type="man">
  <feat name="wnsk" value="atlantic%1:17:00::"/>
  <feat name="text" value="Atlantic"/>
 </struct>
 <struct from="1359" id="n02634545_wf11" to="1363" type="man">
  <feat name="wnsk" value="area%1:15:01::"/>
  <feat name="text" value="area"/>
 </struct>
 <struct from="1371" id="n02634545_wf14" to="1379" type="un">
  <feat name="text" value="northern"/>
 </struct>
 <struct from="1398" id="n02634717_wf2" to="1403" type="man">
  <feat name="wnsk" value="genus%1:14:00::"/>
  <feat name="text" value="genus"/>
 </struct>
 <struct from="1407" id="n02634717_wf4" to="1419" type="auto">
  <feat name="wnsk" value="stromateidae%1:05:00::"/>
  <feat name="text" value="Stromateidae"/>
 </struct>
 <struct from="1421" id="n02634858_wf1" to="1429" type="man">
  <feat name="wnsk" value="sluggish%3:00:00:inactive:01"/>
  <feat name="wnsk" value="sluggish%3:00:01:slow:01"/>
  <feat name="text" value="sluggish"/>
 </struct>
 <struct from="1430" id="n02634858_wf2" to="1443" type="auto">
  <feat name="wnsk" value="square-tailed%3:00:00:caudate:00"/>
  <feat name="text" value="square-tailed"/>
 </struct>
 <struct from="1444" id="n02634858_wf3" to="1448" type="man">
  <feat name="wnsk" value="fish%1:05:00::"/>
  <feat name="text" value="fish"/>
 </struct>
 <struct from="1449" id="n02634858_wf4" to="1456" type="man">
  <feat name="wnsk" value="armored%3:00:02::"/>
  <feat name="text" value="armored"/>
 </struct>
 <struct from="1462" id="n02634858_wf6" to="1467" type="man">
  <feat name="wnsk" value="tough%3:00:02::"/>
  <feat name="text" value="tough"/>
 </struct>
 <struct from="1468" id="n02634858_wf7" to="1472" type="man">
  <feat name="wnsk" value="bony%3:01:00::"/>
  <feat name="text" value="bony"/>
 </struct>
 <struct from="1473" id="n02634858_wf8" to="1479" type="man">
  <feat name="wnsk" value="scale%1:05:00::"/>
  <feat name="text" value="scales"/>
 </struct>
 <struct from="1484" id="n02634858_wf11" to="1488" type="un">
  <feat name="text" value="deep"/>
 </struct>
 <struct from="1489" id="n02634858_wf12" to="1493" type="man">
  <feat name="wnsk" value="warm%3:00:01::"/>
  <feat name="text" value="warm"/>
 </struct>
 <struct from="1494" id="n02634858_wf13" to="1500" type="man">
  <feat name="wnsk" value="water%1:17:00::"/>
  <feat name="text" value="waters"/>
 </struct>
 <struct from="1504" id="n02635013_wf2" to="1509" type="man">
  <feat name="wnsk" value="genus%1:14:00::"/>
  <feat name="text" value="genus"/>
 </struct>
 <struct from="1513" id="n02635013_wf4" to="1525" type="auto">
  <feat name="wnsk" value="stromateidae%1:05:00::"/>
  <feat name="text" value="Stromateidae"/>
 </struct>
 <struct from="1527" id="n02635154_wf1" to="1535" type="auto">
  <feat name="wnsk" value="blackish%3:00:00:achromatic:00"/>
  <feat name="text" value="blackish"/>
 </struct>
 <struct from="1536" id="n02635154_wf2" to="1540" type="man">
  <feat name="wnsk" value="fish%1:05:00::"/>
  <feat name="text" value="fish"/>
 </struct>
 <struct from="1556" id="n02635154_wf6" to="1562" type="man">
  <feat name="wnsk" value="water%1:17:00::"/>
  <feat name="text" value="waters"/>
 </struct>
 <struct from="1564" id="n02635310_wf1" to="1575" type="auto">
  <feat name="wnsk" value="clingfish%1:05:00::"/>
  <feat name="text" value="clingfishes"/>
 </struct>
 <struct from="1595" id="n02635459_wf5" to="1607" type="auto">
  <feat name="wnsk" value="gobiesocidae%1:05:00::"/>
  <feat name="text" value="Gobiesocidae"/>
 </struct>
 <struct from="1609" id="n02635580_wf1" to="1613" type="un">
  <feat name="text" value="very"/>
 </struct>
 <struct from="1614" id="n02635580_wf2" to="1619" type="man">
  <feat name="wnsk" value="small%3:00:00::"/>
  <feat name="text" value="small"/>
 </struct>
 <struct from="1626" id="n02635580_tok4" to="1632" type="un">
  <feat name="text" value="inches"/>
 </struct>
 <struct from="1634" id="n02635580_wf3" to="1643" type="man">
  <feat name="wnsk" value="flattened%3:00:00:planar:00"/>
  <feat name="text" value="flattened"/>
 </struct>
 <struct from="1644" id="n02635580_wf4" to="1650" type="man">
  <feat name="wnsk" value="marine%3:00:00:aquatic:00"/>
  <feat name="text" value="marine"/>
 </struct>
 <struct from="1651" id="n02635580_wf5" to="1655" type="man">
  <feat name="wnsk" value="fish%1:05:00::"/>
  <feat name="text" value="fish"/>
 </struct>
 <struct from="1663" id="n02635580_wf8" to="1670" type="man">
  <feat name="wnsk" value="suck%2:34:04::"/>
  <feat name="text" value="sucking"/>
 </struct>
 <struct from="1671" id="n02635580_wf9" to="1675" type="man">
  <feat name="wnsk" value="disc%1:25:00::"/>
  <feat name="text" value="disc"/>
 </struct>
 <struct from="1683" id="n02635580_wf12" to="1690" type="man">
  <feat name="wnsk" value="abdomen%1:08:00::"/>
  <feat name="text" value="abdomen"/>
 </struct>
 <struct from="1695" id="n02635580_wf14" to="1703" type="man">
  <feat name="wnsk" value="cling%2:35:00::"/>
  <feat name="text" value="clinging"/>
 </struct>
 <struct from="1707" id="n02635580_wf16" to="1712" type="man">
  <feat name="wnsk" value="rock%1:17:01::"/>
  <feat name="text" value="rocks"/>
 </struct>
 <struct from="1713" id="n02635580_wf17" to="1717" type="auto">
  <feat name="wnsk" value="etc.%4:02:00::"/>
  <feat name="text" value="etc."/>
 </struct>
 <struct from="1719" id="n02635781_wf1" to="1728" type="auto">
  <feat name="wnsk" value="clingfish%1:05:00::"/>
  <feat name="text" value="clingfish"/>
 </struct>
 <struct from="1734" id="n02635781_wf3" to="1741" type="man">
  <feat name="wnsk" value="typical%3:00:00::"/>
  <feat name="text" value="typical"/>
 </struct>
 <struct from="1742" id="n02635781_wf4" to="1749" type="auto">
  <feat name="wnsk" value="skillet%1:06:00::"/>
  <feat name="text" value="skillet"/>
 </struct>
 <struct from="1750" id="n02635781_wf5" to="1755" type="man">
  <feat name="wnsk" value="shape%1:07:00::"/>
  <feat name="text" value="shape"/>
 </struct>
 <struct from="1757" id="n02635911_wf1" to="1768" type="auto">
  <feat name="wnsk" value="tripletail%1:05:00::"/>
  <feat name="text" value="tripletails"/>
 </struct>
 <struct from="1788" id="n02636035_wf5" to="1797" type="auto">
  <feat name="wnsk" value="lobotidae%1:05:00::"/>
  <feat name="text" value="Lobotidae"/>
 </struct>
 <struct from="1799" id="n02636170_wf1" to="1804" type="man">
  <feat name="wnsk" value="large%3:00:00::"/>
  <feat name="text" value="large"/>
 </struct>
 <struct from="1818" id="n02636170_wf5" to="1822" type="man">
  <feat name="wnsk" value="warm%3:00:01::"/>
  <feat name="text" value="warm"/>
 </struct>
 <struct from="1823" id="n02636170_wf6" to="1829" type="man">
  <feat name="wnsk" value="water%1:17:00::"/>
  <feat name="text" value="waters"/>
 </struct>
 <struct from="1830" id="n02636170_wf7" to="1839" type="man">
  <feat name="wnsk" value="worldwide%3:00:00:international:00"/>
  <feat name="wnsk" value="worldwide%3:00:00:intercontinental:00"/>
  <feat name="text" value="worldwide"/>
 </struct>
 <struct from="1840" id="n02636170_wf8" to="1846" type="un">
  <feat name="text" value="having"/>
 </struct>
 <struct from="1847" id="n02636170_wf9" to="1851" type="man">
  <feat name="wnsk" value="long%3:00:01::"/>
  <feat name="text" value="long"/>
 </struct>
 <struct from="1896" id="n02636170_wf19" to="1903" type="un">
  <feat name="text" value="suggest"/>
 </struct>
 <struct from="1906" id="n02636170_wf21" to="1917" type="man">
  <feat name="wnsk" value="three-lobed%3:00:00:multilateral:00"/>
  <feat name="text" value="three-lobed"/>
 </struct>
 <struct from="1918" id="n02636170_wf22" to="1922" type="man">
  <feat name="wnsk" value="tail%1:05:00::"/>
  <feat name="text" value="tail"/>
 </struct>
 <struct from="1924" id="n02636405_wf1" to="1934" type="auto">
  <feat name="wnsk" value="tripletail%1:05:00::"/>
  <feat name="text" value="tripletail"/>
 </struct>
 <struct from="1935" id="n02636405_wf2" to="1940" type="un">
  <feat name="text" value="found"/>
 </struct>
 <struct from="1958" id="n02636405_wf7" to="1966" type="un">
  <feat name="text" value="northern"/>
 </struct>
 <struct from="1982" id="n02636550_wf1" to="1992" type="auto">
  <feat name="wnsk" value="tripletail%1:05:00::"/>
  <feat name="text" value="tripletail"/>
 </struct>
 <struct from="1993" id="n02636550_wf2" to="1998" type="un">
  <feat name="text" value="found"/>
 </struct>
 <struct from="2006" id="n02636550_wf5" to="2013" type="man">
  <feat name="wnsk" value="pacific%1:17:00::"/>
  <feat name="text" value="Pacific"/>
 </struct>
 <struct from="2015" id="n02636666_wf1" to="2023" type="auto">
  <feat name="wnsk" value="mojarra%1:05:00::"/>
  <feat name="text" value="mojarras"/>
 </struct>
 <struct from="2025" id="n02636854_wf1" to="2030" type="man">
  <feat name="wnsk" value="small%3:00:00::"/>
  <feat name="text" value="small"/>
 </struct>
 <struct from="2031" id="n02636854_wf2" to="2038" type="man">
  <feat name="wnsk" value="silvery%3:00:00:bright:00"/>
  <feat name="text" value="silvery"/>
 </struct>
 <struct from="2039" id="n02636854_wf3" to="2048" type="man">
  <feat name="wnsk" value="school%2:38:00::"/>
  <feat name="text" value="schooling"/>
 </struct>
 <struct from="2049" id="n02636854_wf4" to="2055" type="man">
  <feat name="wnsk" value="fish%1:05:00::"/>
  <feat name="text" value="fishes"/>
 </struct>
 <struct from="2061" id="n02636854_wf6" to="2072" type="auto">
  <feat name="wnsk" value="protrusible%3:00:00:extensile:00"/>
  <feat name="text" value="protrusible"/>
 </struct>
 <struct from="2073" id="n02636854_wf7" to="2079" type="man">
  <feat name="wnsk" value="mouth%1:08:01::"/>
  <feat name="text" value="mouths"/>
 </struct>
 <struct from="2080" id="n02636854_wf8" to="2085" type="un">
  <feat name="text" value="found"/>
 </struct>
 <struct from="2089" id="n02636854_wf10" to="2093" type="man">
  <feat name="wnsk" value="warm%3:00:01::"/>
  <feat name="text" value="warm"/>
 </struct>
 <struct from="2094" id="n02636854_wf11" to="2101" type="man">
  <feat name="wnsk" value="coastal%3:00:00::"/>
  <feat name="text" value="coastal"/>
 </struct>
 <struct from="2102" id="n02636854_wf12" to="2108" type="man">
  <feat name="wnsk" value="water%1:17:00::"/>
  <feat name="text" value="waters"/>
 </struct>
 <struct from="2128" id="n02637046_wf5" to="2137" type="auto">
  <feat name="wnsk" value="gerreidae%1:05:00::"/>
  <feat name="text" value="Gerreidae"/>
 </struct>
 <struct from="2139" id="n02637179_wf1" to="2146" type="un">
  <feat name="text" value="popular"/>
 </struct>
 <struct from="2147" id="n02637179_wf2" to="2154" type="auto">
  <feat name="wnsk" value="panfish%1:13:00::"/>
  <feat name="text" value="panfish"/>
 </struct>
 <struct from="2160" id="n02637179_wf4" to="2167" type="auto">
  <feat name="wnsk" value="bermuda%1:15:00::"/>
  <feat name="text" value="Bermuda"/>
 </struct>
 <struct from="2190" id="n02637179_wf10" to="2196" type="auto">
  <feat name="wnsk" value="brazil%1:15:00::"/>
  <feat name="text" value="Brazil"/>
 </struct>
 <struct from="2200" id="n02637337_wf2" to="2205" type="man">
  <feat name="wnsk" value="genus%1:14:00::"/>
  <feat name="text" value="genus"/>
 </struct>
 <struct from="2209" id="n02637337_wf4" to="2218" type="auto">
  <feat name="wnsk" value="gerreidae%1:05:00::"/>
  <feat name="text" value="Gerreidae"/>
 </struct>
 <struct from="2220" id="n02637475_wf1" to="2227" type="man">
  <feat name="wnsk" value="silvery%3:00:00:bright:00"/>
  <feat name="text" value="silvery"/>
 </struct>
 <struct from="2228" id="n02637475_wf2" to="2235" type="auto">
  <feat name="wnsk" value="mojarra%1:05:00::"/>
  <feat name="text" value="mojarra"/>
 </struct>
 <struct from="2236" id="n02637475_wf3" to="2241" type="un">
  <feat name="text" value="found"/>
 </struct>
 <struct from="2242" id="n02637475_wf4" to="2247" type="un">
  <feat name="text" value="along"/>
 </struct>
 <struct from="2248" id="n02637475_wf5" to="2253" type="un">
  <feat name="text" value="sandy"/>
 </struct>
 <struct from="2254" id="n02637475_wf6" to="2260" type="man">
  <feat name="wnsk" value="shore%1:17:00::"/>
  <feat name="text" value="shores"/>
 </struct>
 <struct from="2268" id="n02637475_wf9" to="2275" type="man">
  <feat name="wnsk" value="western%3:00:00:west:00"/>
  <feat name="text" value="western"/>
 </struct>
 <struct from="2276" id="n02637475_wf10" to="2284" type="man">
  <feat name="wnsk" value="atlantic%1:17:00::"/>
  <feat name="text" value="Atlantic"/>
 </struct>
 <struct from="2286" id="n02637637_wf1" to="2291" type="man">
  <feat name="wnsk" value="small%3:00:00::"/>
  <feat name="text" value="small"/>
 </struct>
 <struct from="2292" id="n02637637_wf2" to="2298" type="man">
  <feat name="wnsk" value="family%1:14:03::"/>
  <feat name="text" value="family"/>
 </struct>
 <struct from="2302" id="n02637637_wf4" to="2307" type="man">
  <feat name="wnsk" value="small%3:00:00::"/>
  <feat name="text" value="small"/>
 </struct>
 <struct from="2323" id="n02637637_wf8" to="2330" type="man">
  <feat name="wnsk" value="shallow%3:00:01::"/>
  <feat name="text" value="shallow"/>
 </struct>
 <struct from="2331" id="n02637637_wf9" to="2337" type="man">
  <feat name="wnsk" value="water%1:17:00::"/>
  <feat name="text" value="waters"/>
 </struct>
 <struct from="2345" id="n02637637_wf12" to="2352" type="man">
  <feat name="wnsk" value="pacific%1:17:00::"/>
  <feat name="text" value="Pacific"/>
 </struct>
 <struct from="2353" id="n02637637_wf13" to="2359" type="un">
  <feat name="text" value="around"/>
 </struct>
 <struct from="2360" id="n02637637_wf14" to="2369" type="auto">
  <feat name="wnsk" value="indonesia%1:15:00::"/>
  <feat name="text" value="Indonesia"/>
 </struct>
 <struct from="2389" id="n02637839_wf5" to="2401" type="auto">
  <feat name="wnsk" value="sillaginidae%1:05:00::"/>
  <feat name="text" value="Sillaginidae"/>
 </struct>
 <struct from="2405" id="n02637977_wf2" to="2410" type="man">
  <feat name="wnsk" value="small%3:00:00::"/>
  <feat name="text" value="small"/>
 </struct>
 <struct from="2411" id="n02637977_wf3" to="2415" type="man">
  <feat name="wnsk" value="fish%1:05:00::"/>
  <feat name="text" value="fish"/>
 </struct>
 <struct from="2438" id="n02637977_wf9" to="2447" type="auto">
  <feat name="wnsk" value="excellent%3:00:00:superior:02"/>
  <feat name="text" value="excellent"/>
 </struct>
 <struct from="2459" id="n02638104_wf1" to="2464" type="man">
  <feat name="wnsk" value="shiny%3:00:00:bright:00"/>
  <feat name="text" value="shiny"/>
 </struct>
 <struct from="2465" id="n02638104_wf2" to="2474" type="un">
  <feat name="text" value="substance"/>
 </struct>
 <struct from="2480" id="n02638104_wf4" to="2488" type="auto">
  <feat name="wnsk" value="resemble%2:42:00::"/>
  <feat name="text" value="resemble"/>
 </struct>
 <struct from="2489" id="n02638104_wf5" to="2495" type="man">
  <feat name="wnsk" value="enamel%1:06:00::"/>
  <feat name="text" value="enamel"/>
 </struct>
 <struct from="2500" id="n02638104_wf7" to="2502" type="un">
  <feat name="text" value="is"/>
 </struct>
 <struct from="2503" id="n02638104_wf8" to="2511" type="man">
  <feat name="wnsk" value="secrete%2:29:00::"/>
  <feat name="text" value="secreted"/>
 </struct>
 <struct from="2519" id="n02638104_wf11" to="2525" type="auto">
  <feat name="wnsk" value="corium%1:08:00::"/>
  <feat name="text" value="corium"/>
 </struct>
 <struct from="2529" id="n02638104_wf13" to="2536" type="un">
  <feat name="text" value="certain"/>
 </struct>
 <struct from="2537" id="n02638104_wf14" to="2543" type="man">
  <feat name="wnsk" value="fish%1:05:00::"/>
  <feat name="text" value="fishes"/>
 </struct>
 <struct from="2575" id="n02638104_wf21" to="2583" type="un">
  <feat name="text" value="composes"/>
 </struct>
 <struct from="2588" id="n02638104_wf23" to="2593" type="un">
  <feat name="text" value="outer"/>
 </struct>
 <struct from="2594" id="n02638104_wf24" to="2599" type="man">
  <feat name="wnsk" value="layer%1:06:00::"/>
  <feat name="text" value="layer"/>
 </struct>
 <struct from="2609" id="n02638104_wf27" to="2615" type="man">
  <feat name="wnsk" value="scale%1:05:00::"/>
  <feat name="text" value="scales"/>
 </struct>
 <struct from="2619" id="n02638323_wf2" to="2624" type="man">
  <feat name="wnsk" value="group%1:03:00::"/>
  <feat name="text" value="group"/>
 </struct>
 <struct from="2628" id="n02638323_wf4" to="2634" type="un">
  <feat name="text" value="mostly"/>
 </struct>
 <struct from="2635" id="n02638323_wf5" to="2642" type="un">
  <feat name="text" value="extinct"/>
 </struct>
 <struct from="2643" id="n02638323_wf6" to="2652" type="un">
  <feat name="text" value="primitive"/>
 </struct>
 <struct from="2665" id="n02638323_wf9" to="2678" type="un">
  <feat name="text" value="characterized"/>
 </struct>
 <struct from="2682" id="n02638323_wf11" to="2687" type="un">
  <feat name="text" value="armor"/>
 </struct>
 <struct from="2688" id="n02638323_wf12" to="2692" type="un">
  <feat name="text" value="like"/>
 </struct>
 <struct from="2693" id="n02638323_wf13" to="2697" type="man">
  <feat name="wnsk" value="bony%3:01:00::"/>
  <feat name="text" value="bony"/>
 </struct>
 <struct from="2698" id="n02638323_wf14" to="2704" type="man">
  <feat name="wnsk" value="scale%1:05:00::"/>
  <feat name="text" value="scales"/>
 </struct>
 <struct from="2706" id="n02638596_wf1" to="2715" type="un">
  <feat name="text" value="primitive"/>
 </struct>
 <struct from="2716" id="n02638596_wf2" to="2722" type="man">
  <feat name="wnsk" value="fish%1:05:00::"/>
  <feat name="text" value="fishes"/>
 </struct>
 <struct from="2723" id="n02638596_wf3" to="2729" type="un">
  <feat name="text" value="having"/>
 </struct>
 <struct from="2730" id="n02638596_wf4" to="2735" type="un">
  <feat name="text" value="thick"/>
 </struct>
 <struct from="2736" id="n02638596_wf5" to="2740" type="man">
  <feat name="wnsk" value="bony%3:01:00::"/>
  <feat name="text" value="bony"/>
 </struct>
 <struct from="2741" id="n02638596_wf6" to="2747" type="man">
  <feat name="wnsk" value="scale%1:05:00::"/>
  <feat name="text" value="scales"/>
 </struct>
 <struct from="2755" id="n02638596_wf9" to="2760" type="man">
  <feat name="wnsk" value="shiny%3:00:00:bright:00"/>
  <feat name="text" value="shiny"/>
 </struct>
 <struct from="2761" id="n02638596_wf10" to="2769" type="man">
  <feat name="wnsk" value="covering%1:17:00::"/>
  <feat name="text" value="covering"/>
 </struct>
 <struct from="2771" id="n02638835_wf1" to="2775" type="un">
  <feat name="text" value="only"/>
 </struct>
 <struct from="2780" id="n02638835_wf3" to="2787" type="auto">
  <feat name="wnsk" value="bowfin%1:05:00::"/>
  <feat name="text" value="bowfins"/>
 </struct>
 <struct from="2807" id="n02638960_wf5" to="2814" type="auto">
  <feat name="wnsk" value="amiidae%1:05:00::"/>
  <feat name="text" value="Amiidae"/>
 </struct>
 <struct from="2816" id="n02639087_wf1" to="2825" type="un">
  <feat name="text" value="primitive"/>
 </struct>
 <struct from="2826" id="n02639087_wf2" to="2837" type="man">
  <feat name="wnsk" value="long-bodied%3:00:00:bodied:00"/>
  <feat name="text" value="long-bodied"/>
 </struct>
 <struct from="2838" id="n02639087_wf3" to="2849" type="man">
  <feat name="wnsk" value="carnivorous%3:01:00::"/>
  <feat name="text" value="carnivorous"/>
 </struct>
 <struct from="2873" id="n02639087_wf8" to="2877" type="un">
  <feat name="text" value="very"/>
 </struct>
 <struct from="2878" id="n02639087_wf9" to="2882" type="man">
  <feat name="wnsk" value="long%3:00:01::"/>
  <feat name="text" value="long"/>
 </struct>
 <struct from="2895" id="n02639087_wf13" to="2900" type="un">
  <feat name="text" value="found"/>
 </struct>
 <struct from="2904" id="n02639087_wf15" to="2912" type="man">
  <feat name="wnsk" value="sluggish%3:00:01:slow:01"/>
  <feat name="text" value="sluggish"/>
 </struct>
 <struct from="2913" id="n02639087_wf16" to="2919" type="man">
  <feat name="wnsk" value="water%1:17:00::"/>
  <feat name="text" value="waters"/>
 </struct>
 <struct from="2938" id="n02639312_wf1" to="2950" type="auto">
  <feat name="wnsk" value="paddlefish%1:05:00::"/>
  <feat name="text" value="paddlefishes"/>
 </struct>
 <struct from="2970" id="n02639464_wf5" to="2983" type="auto">
  <feat name="wnsk" value="polyodontidae%1:05:00::"/>
  <feat name="text" value="Polyodontidae"/>
 </struct>
 <struct from="2985" id="n02639605_wf1" to="2994" type="un">
  <feat name="text" value="primitive"/>
 </struct>
 <struct from="2995" id="n02639605_wf2" to="2999" type="man">
  <feat name="wnsk" value="fish%1:05:00::"/>
  <feat name="text" value="fish"/>
 </struct>
 <struct from="3007" id="n02639605_wf5" to="3018" type="man">
  <feat name="wnsk" value="mississippi%1:17:00::"/>
  <feat name="text" value="Mississippi"/>
 </struct>
 <struct from="3019" id="n02639605_wf6" to="3025" type="auto">
  <feat name="wnsk" value="valley%1:17:00::"/>
  <feat name="text" value="valley"/>
 </struct>
 <struct from="3026" id="n02639605_wf7" to="3032" type="un">
  <feat name="text" value="having"/>
 </struct>
 <struct from="3035" id="n02639605_wf9" to="3039" type="man">
  <feat name="wnsk" value="long%3:00:01::"/>
  <feat name="text" value="long"/>
 </struct>
 <struct from="3040" id="n02639605_wf10" to="3053" type="auto">
  <feat name="wnsk" value="paddle-shaped%3:00:00:formed:00"/>
  <feat name="text" value="paddle-shaped"/>
 </struct>
 <struct from="3054" id="n02639605_wf11" to="3059" type="man">
  <feat name="wnsk" value="snout%1:05:00::"/>
  <feat name="text" value="snout"/>
 </struct>
 <struct from="3063" id="n02639786_wf2" to="3068" type="man">
  <feat name="wnsk" value="genus%1:14:00::"/>
  <feat name="text" value="genus"/>
 </struct>
 <struct from="3072" id="n02639786_wf4" to="3085" type="auto">
  <feat name="wnsk" value="polyodontidae%1:05:00::"/>
  <feat name="text" value="Polyodontidae"/>
 </struct>
 <struct from="3087" id="n02639922_wf1" to="3091" type="man">
  <feat name="wnsk" value="fish%1:05:00::"/>
  <feat name="text" value="fish"/>
 </struct>
 <struct from="3095" id="n02639922_wf3" to="3101" type="man">
  <feat name="wnsk" value="large%3:00:00::"/>
  <feat name="wnsk" value="larger%3:00:00:large:00"/>
  <feat name="text" value="larger"/>
 </struct>
 <struct from="3102" id="n02639922_wf4" to="3108" type="auto">
  <feat name="wnsk" value="river%1:17:00::"/>
  <feat name="text" value="rivers"/>
 </struct>
 <struct from="3112" id="n02639922_wf6" to="3117" type="man">
  <feat name="wnsk" value="china%1:15:00::"/>
  <feat name="text" value="China"/>
 </struct>
 <struct from="3118" id="n02639922_wf7" to="3125" type="un">
  <feat name="text" value="similar"/>
 </struct>
 <struct from="3133" id="n02639922_wf10" to="3144" type="man">
  <feat name="wnsk" value="mississippi%1:17:00::"/>
  <feat name="text" value="Mississippi"/>
 </struct>
 <struct from="3145" id="n02639922_wf11" to="3155" type="auto">
  <feat name="wnsk" value="paddlefish%1:05:00::"/>
  <feat name="text" value="paddlefish"/>
 </struct>
 <struct from="3157" id="n02640093_wf1" to="3166" type="auto">
  <feat name="wnsk" value="sturgeon%1:05:00::"/>
  <feat name="text" value="sturgeons"/>
 </struct>
 <struct from="3168" id="n02640242_wf1" to="3173" type="man">
  <feat name="wnsk" value="large%3:00:00::"/>
  <feat name="text" value="large"/>
 </struct>
 <struct from="3174" id="n02640242_wf2" to="3183" type="un">
  <feat name="text" value="primitive"/>
 </struct>
 <struct from="3184" id="n02640242_wf3" to="3190" type="man">
  <feat name="wnsk" value="fish%1:05:00::"/>
  <feat name="text" value="fishes"/>
 </struct>
 <struct from="3191" id="n02640242_wf4" to="3197" type="un">
  <feat name="text" value="valued"/>
 </struct>
 <struct from="3208" id="n02640242_wf7" to="3213" type="man">
  <feat name="wnsk" value="flesh%1:08:02::"/>
  <feat name="text" value="flesh"/>
 </struct>
 <struct from="3218" id="n02640242_wf9" to="3221" type="un">
  <feat name="text" value="roe"/>
 </struct>
 <struct from="3289" id="n02640453_wf5" to="3302" type="auto">
  <feat name="wnsk" value="acipenseridae%1:05:00::"/>
  <feat name="text" value="Acipenseridae"/>
 </struct>
 <struct from="3304" id="n02640453_wf7" to="3313" type="auto">
  <feat name="wnsk" value="sturgeon%1:05:00::"/>
  <feat name="text" value="sturgeons"/>
 </struct>
 <struct from="3337" id="n02640626_wf6" to="3343" type="man">
  <feat name="wnsk" value="marine%3:00:00:aquatic:00"/>
  <feat name="text" value="marine"/>
 </struct>
 <struct from="3364" id="n02640626_wf11" to="3376" type="man">
  <feat name="wnsk" value="northwestern%3:00:00:north:00"/>
  <feat name="text" value="northwestern"/>
 </struct>
 <struct from="3377" id="n02640626_wf12" to="3382" type="man">
  <feat name="wnsk" value="coast%1:17:00::"/>
  <feat name="text" value="coast"/>
 </struct>
 <struct from="3401" id="n02640857_wf1" to="3409" type="un">
  <feat name="text" value="valuable"/>
 </struct>
 <struct from="3410" id="n02640857_wf2" to="3416" type="man">
  <feat name="wnsk" value="source%1:15:00::"/>
  <feat name="text" value="source"/>
 </struct>
 <struct from="3420" id="n02640857_wf4" to="3426" type="auto">
  <feat name="wnsk" value="caviar%1:13:00::"/>
  <feat name="text" value="caviar"/>
 </struct>
 <struct from="3431" id="n02640857_wf6" to="3440" type="auto">
  <feat name="wnsk" value="isinglass%1:27:00::"/>
  <feat name="text" value="isinglass"/>
 </struct>
 <struct from="3442" id="n02640857_wf8" to="3447" type="un">
  <feat name="text" value="found"/>
 </struct>
 <struct from="3451" id="n02640857_wf10" to="3456" type="man">
  <feat name="wnsk" value="purposefully_ignored%0:00:00::"/>
  <feat name="text" value="Black"/>
 </struct>
 <struct from="3461" id="n02640857_wf12" to="3468" type="man">
  <feat name="wnsk" value="caspian%1:17:00::"/>
  <feat name="text" value="Caspian"/>
 </struct>
 <struct from="3469" id="n02640857_wf13" to="3473" type="man">
  <feat name="wnsk" value="sea%1:17:00::"/>
  <feat name="text" value="seas"/>
 </struct>
 <struct from="3475" id="n02641063_wf1" to="3484" type="un">
  <feat name="text" value="comprises"/>
 </struct>
 <struct from="3526" id="n02641215_wf5" to="3539" type="auto">
  <feat name="wnsk" value="lepisosteidae%1:05:00::"/>
  <feat name="text" value="Lepisosteidae"/>
 </struct>
 <struct from="3541" id="n02641215_wf7" to="3551" type="un">
  <feat name="text" value="freshwater"/>
 </struct>
 <struct from="3552" id="n02641215_wf8" to="3556" type="man">
  <feat name="wnsk" value="gar%1:05:01::"/>
  <feat name="text" value="gars"/>
 </struct>
 <struct from="3558" id="n02641379_wf1" to="3567" type="un">
  <feat name="text" value="primitive"/>
 </struct>
 <struct from="3568" id="n02641379_wf2" to="3578" type="man">
  <feat name="wnsk" value="predaceous%3:00:00:carnivorous:00"/>
  <feat name="text" value="predaceous"/>
 </struct>
 <struct from="3594" id="n02641379_wf5" to="3598" type="man">
  <feat name="wnsk" value="fish%1:05:00::"/>
  <feat name="text" value="fish"/>
 </struct>
 <struct from="3599" id="n02641379_wf6" to="3606" type="man">
  <feat name="wnsk" value="covered%3:00:00::"/>
  <feat name="text" value="covered"/>
 </struct>
 <struct from="3612" id="n02641379_wf8" to="3616" type="un">
  <feat name="text" value="hard"/>
 </struct>
 <struct from="3617" id="n02641379_wf9" to="3623" type="man">
  <feat name="wnsk" value="scale%1:05:00::"/>
  <feat name="text" value="scales"/>
 </struct>
 <struct from="3628" id="n02641379_wf11" to="3634" type="un">
  <feat name="text" value="having"/>
 </struct>
 <struct from="3635" id="n02641379_wf12" to="3639" type="man">
  <feat name="wnsk" value="long%3:00:01::"/>
  <feat name="text" value="long"/>
 </struct>
 <struct from="3640" id="n02641379_wf13" to="3644" type="man">
  <feat name="wnsk" value="jaw%1:08:00::"/>
  <feat name="text" value="jaws"/>
 </struct>
 <struct from="3650" id="n02641379_wf15" to="3660" type="auto">
  <feat name="wnsk" value="needlelike%3:00:00:pointed:00"/>
  <feat name="text" value="needlelike"/>
 </struct>
 <struct from="3661" id="n02641379_wf16" to="3666" type="man">
  <feat name="wnsk" value="tooth%1:08:00::"/>
  <feat name="text" value="teeth"/>
 </struct>
 <struct from="3668" id="n02641608_wf1" to="3682" type="auto">
  <feat name="wnsk" value="scorpionfish%1:05:00::"/>
  <feat name="text" value="scorpionfishes"/>
 </struct>
 <struct from="3684" id="n02641608_wf3" to="3692" type="auto">
  <feat name="wnsk" value="sculpin%1:05:00::"/>
  <feat name="text" value="sculpins"/>
 </struct>
 <struct from="3694" id="n02641608_wf5" to="3702" type="auto">
  <feat name="wnsk" value="gurnard%1:05:00::"/>
  <feat name="text" value="gurnards"/>
 </struct>
 <struct from="3704" id="n02641608_wf7" to="3714" type="auto">
  <feat name="wnsk" value="greenling%1:05:01::"/>
  <feat name="text" value="greenlings"/>
 </struct>
 <struct from="3733" id="n02641825_wf1" to="3745" type="auto">
  <feat name="wnsk" value="mail-cheeked%3:00:00:armored:01"/>
  <feat name="text" value="mail-cheeked"/>
 </struct>
 <struct from="3746" id="n02641825_wf2" to="3752" type="man">
  <feat name="wnsk" value="fish%1:05:00::"/>
  <feat name="text" value="fishes"/>
 </struct>
 <struct from="3754" id="n02641825_wf4" to="3768" type="auto">
  <feat name="wnsk" value="scorpionfish%1:05:00::"/>
  <feat name="text" value="scorpionfishes"/>
 </struct>
 <struct from="3770" id="n02641825_wf6" to="3778" type="auto">
  <feat name="wnsk" value="gurnard%1:05:00::"/>
  <feat name="text" value="gurnards"/>
 </struct>
 <struct from="3780" id="n02642107_wf1" to="3786" type="man">
  <feat name="wnsk" value="fish%1:05:00::"/>
  <feat name="text" value="fishes"/>
 </struct>
 <struct from="3787" id="n02642107_wf2" to="3793" type="un">
  <feat name="text" value="having"/>
 </struct>
 <struct from="3798" id="n02642107_wf4" to="3802" type="man">
  <feat name="wnsk" value="head%1:08:00::"/>
  <feat name="text" value="head"/>
 </struct>
 <struct from="3803" id="n02642107_wf5" to="3810" type="man">
  <feat name="wnsk" value="armored%3:00:02::"/>
  <feat name="text" value="armored"/>
 </struct>
 <struct from="3816" id="n02642107_wf7" to="3820" type="man">
  <feat name="wnsk" value="bony%3:01:00::"/>
  <feat name="text" value="bony"/>
 </struct>
 <struct from="3821" id="n02642107_wf8" to="3827" type="man">
  <feat name="wnsk" value="plate%1:08:00::"/>
  <feat name="text" value="plates"/>
 </struct>
 <struct from="3829" id="n02642430_wf1" to="3843" type="auto">
  <feat name="wnsk" value="scorpionfish%1:05:00::"/>
  <feat name="text" value="scorpionfishes"/>
 </struct>
 <struct from="3845" id="n02642430_wf3" to="3855" type="man">
  <feat name="wnsk" value="rockfish%1:05:01::"/>
  <feat name="text" value="rockfishes"/>
 </struct>
 <struct from="3857" id="n02642430_wf5" to="3867" type="auto">
  <feat name="wnsk" value="lionfish%1:05:00::"/>
  <feat name="text" value="lionfishes"/>
 </struct>
 <struct from="3876" id="n02642644_wf3" to="3884" type="auto">
  <feat name="wnsk" value="numerous%3:00:00:many:00"/>
  <feat name="text" value="numerous"/>
 </struct>
 <struct from="3885" id="n02642644_wf4" to="3896" type="man">
  <feat name="wnsk" value="carnivorous%3:01:00::"/>
  <feat name="text" value="carnivorous"/>
 </struct>
 <struct from="3897" id="n02642644_wf5" to="3904" type="auto">
  <feat name="wnsk" value="usually%4:02:00::"/>
  <feat name="text" value="usually"/>
 </struct>
 <struct from="3905" id="n02642644_wf6" to="3920" type="auto">
  <feat name="wnsk" value="bottom-dwelling%3:01:00::"/>
  <feat name="text" value="bottom-dwelling"/>
 </struct>
 <struct from="3921" id="n02642644_wf7" to="3925" type="man">
  <feat name="wnsk" value="warm%3:00:01::"/>
  <feat name="text" value="warm"/>
 </struct>
 <struct from="3926" id="n02642644_wf8" to="3931" type="man">
  <feat name="wnsk" value="water%1:17:00::"/>
  <feat name="text" value="water"/>
 </struct>
 <struct from="3932" id="n02642644_wf9" to="3938" type="man">
  <feat name="wnsk" value="marine%3:00:00:aquatic:00"/>
  <feat name="text" value="marine"/>
 </struct>
 <struct from="3939" id="n02642644_wf10" to="3945" type="man">
  <feat name="wnsk" value="fish%1:05:00::"/>
  <feat name="text" value="fishes"/>
 </struct>
 <struct from="3946" id="n02642644_wf11" to="3951" type="un">
  <feat name="text" value="found"/>
 </struct>
 <struct from="3952" id="n02642644_wf12" to="3961" type="man">
  <feat name="wnsk" value="worldwide%3:00:00:intercontinental:00"/>
  <feat name="wnsk" value="worldwide%3:00:00:international:00"/>
  <feat name="text" value="worldwide"/>
 </struct>
 <struct from="3966" id="n02642644_wf14" to="3970" type="un">
  <feat name="text" value="most"/>
 </struct>
 <struct from="3971" id="n02642644_wf15" to="3979" type="auto">
  <feat name="wnsk" value="abundant%3:00:00::"/>
  <feat name="text" value="abundant"/>
 </struct>
 <struct from="3987" id="n02642644_wf18" to="3994" type="man">
  <feat name="wnsk" value="pacific%1:17:00::"/>
  <feat name="text" value="Pacific"/>
 </struct>
 <struct from="4014" id="n02642935_wf5" to="4026" type="auto">
  <feat name="wnsk" value="scorpaenidae%1:05:00::"/>
  <feat name="text" value="Scorpaenidae"/>
 </struct>
 <struct from="4028" id="n02642935_wf7" to="4042" type="auto">
  <feat name="wnsk" value="scorpionfish%1:05:00::"/>
  <feat name="text" value="scorpionfishes"/>
 </struct>
 <struct from="4044" id="n02643112_wf1" to="4050" type="man">
  <feat name="wnsk" value="marine%3:00:00:aquatic:00"/>
  <feat name="text" value="marine"/>
 </struct>
 <struct from="4051" id="n02643112_wf2" to="4057" type="man">
  <feat name="wnsk" value="fish%1:05:00::"/>
  <feat name="text" value="fishes"/>
 </struct>
 <struct from="4058" id="n02643112_wf3" to="4064" type="un">
  <feat name="text" value="having"/>
 </struct>
 <struct from="4067" id="n02643112_wf5" to="4075" type="man">
  <feat name="wnsk" value="tapering%3:00:00:narrow:00"/>
  <feat name="text" value="tapering"/>
 </struct>
 <struct from="4076" id="n02643112_wf6" to="4080" type="man">
  <feat name="wnsk" value="body%1:08:01::"/>
  <feat name="text" value="body"/>
 </struct>
 <struct from="4089" id="n02643112_wf9" to="4096" type="man">
  <feat name="wnsk" value="armored%3:00:02::"/>
  <feat name="text" value="armored"/>
 </struct>
 <struct from="4097" id="n02643112_wf10" to="4101" type="man">
  <feat name="wnsk" value="head%1:08:00::"/>
  <feat name="text" value="head"/>
 </struct>
 <struct from="4106" id="n02643112_wf12" to="4114" type="man">
  <feat name="wnsk" value="venomous%3:00:00:toxic:00"/>
  <feat name="text" value="venomous"/>
 </struct>
 <struct from="4115" id="n02643112_wf13" to="4121" type="man">
  <feat name="wnsk" value="spine%1:05:00::"/>
  <feat name="text" value="spines"/>
 </struct>
 <struct from="4125" id="n02643316_wf2" to="4129" type="man">
  <feat name="wnsk" value="kind%1:09:00::"/>
  <feat name="text" value="kind"/>
 </struct>
 <struct from="4133" id="n02643316_wf4" to="4145" type="auto">
  <feat name="wnsk" value="scorpionfish%1:05:00::"/>
  <feat name="text" value="scorpionfish"/>
 </struct>
 <struct from="4147" id="n02643448_wf1" to="4157" type="auto">
  <feat name="wnsk" value="lionfish%1:05:00::"/>
  <feat name="text" value="lionfishes"/>
 </struct>
 <struct from="4159" id="n02643566_wf1" to="4167" type="auto">
  <feat name="wnsk" value="brightly%4:02:00::"/>
  <feat name="text" value="brightly"/>
 </struct>
 <struct from="4168" id="n02643566_wf2" to="4175" type="man">
  <feat name="wnsk" value="striped%3:00:00:patterned:00"/>
  <feat name="text" value="striped"/>
 </struct>
 <struct from="4176" id="n02643566_wf3" to="4180" type="man">
  <feat name="wnsk" value="fish%1:05:00::"/>
  <feat name="text" value="fish"/>
 </struct>
 <struct from="4188" id="n02643566_wf6" to="4196" type="un">
  <feat name="text" value="tropical"/>
 </struct>
 <struct from="4197" id="n02643566_wf7" to="4204" type="man">
  <feat name="wnsk" value="pacific%1:17:00::"/>
  <feat name="text" value="Pacific"/>
 </struct>
 <struct from="4205" id="n02643566_wf8" to="4211" type="un">
  <feat name="text" value="having"/>
 </struct>
 <struct from="4212" id="n02643566_wf9" to="4221" type="man">
  <feat name="wnsk" value="elongated%3:00:00:long:01"/>
  <feat name="text" value="elongated"/>
 </struct>
 <struct from="4222" id="n02643566_wf10" to="4227" type="un">
  <feat name="text" value="spiny"/>
 </struct>
 <struct from="4228" id="n02643566_wf11" to="4232" type="un">
  <feat name="text" value="fins"/>
 </struct>
 <struct from="4234" id="n02643713_wf1" to="4245" type="auto">
  <feat name="wnsk" value="stonefish%1:05:00::"/>
  <feat name="text" value="stonefishes"/>
 </struct>
 <struct from="4247" id="n02643836_wf1" to="4255" type="man">
  <feat name="wnsk" value="venomous%3:00:00:toxic:00"/>
  <feat name="text" value="venomous"/>
 </struct>
 <struct from="4256" id="n02643836_wf2" to="4264" type="un">
  <feat name="text" value="tropical"/>
 </struct>
 <struct from="4265" id="n02643836_wf3" to="4271" type="man">
  <feat name="wnsk" value="marine%3:00:00:aquatic:00"/>
  <feat name="text" value="marine"/>
 </struct>
 <struct from="4272" id="n02643836_wf4" to="4276" type="man">
  <feat name="wnsk" value="fish%1:05:00::"/>
  <feat name="text" value="fish"/>
 </struct>
 <struct from="4277" id="n02643836_wf5" to="4287" type="auto">
  <feat name="wnsk" value="resemble%2:42:00::"/>
  <feat name="text" value="resembling"/>
 </struct>
 <struct from="4290" id="n02643836_wf7" to="4295" type="un">
  <feat name="text" value="piece"/>
 </struct>
 <struct from="4299" id="n02643836_wf9" to="4303" type="man">
  <feat name="wnsk" value="rock%1:17:01::"/>
  <feat name="text" value="rock"/>
 </struct>
 <struct from="4305" id="n02643989_wf1" to="4315" type="man">
  <feat name="wnsk" value="rockfish%1:05:01::"/>
  <feat name="text" value="rockfishes"/>
 </struct>
 <struct from="4317" id="n02644113_wf1" to="4323" type="man">
  <feat name="wnsk" value="marine%3:00:00:aquatic:00"/>
  <feat name="text" value="marine"/>
 </struct>
 <struct from="4334" id="n02644113_wf4" to="4339" type="un">
  <feat name="text" value="found"/>
 </struct>
 <struct from="4346" id="n02644113_wf6" to="4351" type="man">
  <feat name="wnsk" value="rock%1:17:01::"/>
  <feat name="text" value="rocks"/>
 </struct>
 <struct from="4352" id="n02644113_wf7" to="4357" type="un">
  <feat name="text" value="along"/>
 </struct>
 <struct from="4362" id="n02644113_wf9" to="4370" type="un">
  <feat name="text" value="northern"/>
 </struct>
 <struct from="4371" id="n02644113_wf10" to="4377" type="man">
  <feat name="wnsk" value="coast%1:17:00::"/>
  <feat name="text" value="coasts"/>
 </struct>
 <struct from="4381" id="n02644113_wf12" to="4387" type="man">
  <feat name="wnsk" value="europe%1:17:00::"/>
  <feat name="text" value="Europe"/>
 </struct>
 <struct from="4392" id="n02644113_wf14" to="4399" type="man">
  <feat name="wnsk" value="america%1:17:00::"/>
  <feat name="text" value="America"/>
 </struct>
 <struct from="4403" id="n02644360_wf2" to="4411" type="man">
  <feat name="wnsk" value="rockfish%1:05:01::"/>
  <feat name="text" value="rockfish"/>
 </struct>
 <struct from="4419" id="n02644360_wf5" to="4426" type="man">
  <feat name="wnsk" value="pacific%3:01:00::"/>
  <feat name="text" value="Pacific"/>
 </struct>
 <struct from="4427" id="n02644360_wf6" to="4434" type="man">
  <feat name="wnsk" value="coastal%3:00:00::"/>
  <feat name="text" value="coastal"/>
 </struct>
 <struct from="4435" id="n02644360_wf7" to="4441" type="man">
  <feat name="wnsk" value="water%1:17:00::"/>
  <feat name="text" value="waters"/>
 </struct>
 <struct from="4462" id="n02644501_wf2" to="4474" type="auto">
  <feat name="wnsk" value="commercially%4:02:00::"/>
  <feat name="text" value="commercially"/>
 </struct>
 <struct from="4475" id="n02644501_wf3" to="4484" type="un">
  <feat name="text" value="important"/>
 </struct>
 <struct from="4485" id="n02644501_wf4" to="4489" type="man">
  <feat name="wnsk" value="fish%1:05:00::"/>
  <feat name="text" value="fish"/>
 </struct>
 <struct from="4531" id="n02644665_wf2" to="4536" type="man">
  <feat name="wnsk" value="large%3:00:00::"/>
  <feat name="text" value="large"/>
 </struct>
 <struct from="4537" id="n02644665_wf3" to="4541" type="man">
  <feat name="wnsk" value="fish%1:05:00::"/>
  <feat name="text" value="fish"/>
 </struct>
 <struct from="4581" id="n02644817_wf1" to="4586" type="man">
  <feat name="wnsk" value="large%3:00:00::"/>
  <feat name="text" value="large"/>
 </struct>
 <struct from="4587" id="n02644817_wf2" to="4591" type="man">
  <feat name="wnsk" value="fish%1:05:00::"/>
  <feat name="text" value="fish"/>
 </struct>
 <struct from="4595" id="n02644817_wf4" to="4603" type="un">
  <feat name="text" value="northern"/>
 </struct>
 <struct from="4623" id="n02644817_wf8" to="4630" type="man">
  <feat name="wnsk" value="america%1:17:00::"/>
  <feat name="text" value="America"/>
 </struct>
 <struct from="4635" id="n02644817_wf10" to="4641" type="man">
  <feat name="wnsk" value="europe%1:17:00::"/>
  <feat name="text" value="Europe"/>
 </struct>
 <struct from="4643" id="n02644967_wf1" to="4651" type="auto">
  <feat name="wnsk" value="sculpin%1:05:00::"/>
  <feat name="text" value="sculpins"/>
 </struct>
 <struct from="4671" id="n02645143_wf5" to="4679" type="auto">
  <feat name="wnsk" value="cottidae%1:05:00::"/>
  <feat name="text" value="Cottidae"/>
 </struct>
 <struct from="4681" id="n02645143_wf7" to="4689" type="auto">
  <feat name="wnsk" value="sculpin%1:05:00::"/>
  <feat name="text" value="sculpins"/>
 </struct>
 <struct from="4698" id="n02645304_wf3" to="4706" type="auto">
  <feat name="wnsk" value="numerous%3:00:00:many:00"/>
  <feat name="text" value="numerous"/>
 </struct>
 <struct from="4707" id="n02645304_wf4" to="4712" type="un">
  <feat name="text" value="spiny"/>
 </struct>
 <struct from="4713" id="n02645304_wf5" to="4725" type="auto">
  <feat name="wnsk" value="large-headed%3:00:00:headed:01"/>
  <feat name="text" value="large-headed"/>
 </struct>
 <struct from="4726" id="n02645304_wf6" to="4733" type="auto">
  <feat name="wnsk" value="usually%4:02:00::"/>
  <feat name="text" value="usually"/>
 </struct>
 <struct from="4734" id="n02645304_wf7" to="4743" type="auto">
  <feat name="wnsk" value="scaleless%3:00:00:unarmored:02"/>
  <feat name="text" value="scaleless"/>
 </struct>
 <struct from="4768" id="n02645304_wf11" to="4773" type="un">
  <feat name="text" value="broad"/>
 </struct>
 <struct from="4774" id="n02645304_wf12" to="4780" type="man">
  <feat name="wnsk" value="mouth%1:08:01::"/>
  <feat name="text" value="mouths"/>
 </struct>
 <struct from="4782" id="n02645538_wf1" to="4792" type="un">
  <feat name="text" value="freshwater"/>
 </struct>
 <struct from="4793" id="n02645538_wf2" to="4800" type="auto">
  <feat name="wnsk" value="sculpin%1:05:00::"/>
  <feat name="text" value="sculpin"/>
 </struct>
 <struct from="4808" id="n02645538_wf5" to="4813" type="man">
  <feat name="wnsk" value="large%3:00:00::"/>
  <feat name="text" value="large"/>
 </struct>
 <struct from="4814" id="n02645538_wf6" to="4823" type="man">
  <feat name="wnsk" value="flattened%3:00:00:planar:00"/>
  <feat name="text" value="flattened"/>
 </struct>
 <struct from="4824" id="n02645538_wf7" to="4835" type="auto">
  <feat name="wnsk" value="bony-plated%3:00:00:armored:01"/>
  <feat name="text" value="bony-plated"/>
 </struct>
 <struct from="4836" id="n02645538_wf8" to="4840" type="man">
  <feat name="wnsk" value="head%1:08:00::"/>
  <feat name="text" value="head"/>
 </struct>
 <struct from="4846" id="n02645538_wf10" to="4854" type="auto">
  <feat name="wnsk" value="hornlike%3:00:00:hard:01"/>
  <feat name="text" value="hornlike"/>
 </struct>
 <struct from="4855" id="n02645538_wf11" to="4861" type="man">
  <feat name="wnsk" value="spine%1:05:00::"/>
  <feat name="text" value="spines"/>
 </struct>
 <struct from="4863" id="n02645691_wf1" to="4868" type="man">
  <feat name="wnsk" value="small%3:00:00::"/>
  <feat name="text" value="small"/>
 </struct>
 <struct from="4869" id="n02645691_wf2" to="4879" type="un">
  <feat name="text" value="freshwater"/>
 </struct>
 <struct from="4880" id="n02645691_wf3" to="4887" type="auto">
  <feat name="wnsk" value="sculpin%1:05:00::"/>
  <feat name="text" value="sculpin"/>
 </struct>
 <struct from="4891" id="n02645691_wf5" to="4897" type="man">
  <feat name="wnsk" value="europe%1:17:00::"/>
  <feat name="text" value="Europe"/>
 </struct>
 <struct from="4929" id="n02645953_wf1" to="4934" type="man">
  <feat name="wnsk" value="large%3:00:00::"/>
  <feat name="text" value="large"/>
 </struct>
 <struct from="4935" id="n02645953_wf2" to="4942" type="auto">
  <feat name="wnsk" value="sculpin%1:05:00::"/>
  <feat name="text" value="sculpin"/>
 </struct>
 <struct from="4946" id="n02645953_wf4" to="4953" type="man">
  <feat name="wnsk" value="western%3:00:00:west:00"/>
  <feat name="text" value="western"/>
 </struct>
 <struct from="4954" id="n02645953_wf5" to="4962" type="man">
  <feat name="wnsk" value="atlantic%1:17:00::"/>
  <feat name="text" value="Atlantic"/>
 </struct>
 <struct from="4964" id="n02645953_wf7" to="4972" type="man">
  <feat name="wnsk" value="inflate%2:30:02::"/>
  <feat name="text" value="inflates"/>
 </struct>
 <struct from="4985" id="n02645953_wf10" to="4991" type="man">
  <feat name="wnsk" value="catch%2:35:03::"/>
  <feat name="text" value="caught"/>
 </struct>
 <struct from="4993" id="n02646117_wf1" to="4999" type="man">
  <feat name="wnsk" value="grubby%1:05:00::"/>
  <feat name="text" value="grubby"/>
 </struct>
 <struct from="5001" id="n02646241_wf1" to="5006" type="man">
  <feat name="wnsk" value="small%3:00:00::"/>
  <feat name="text" value="small"/>
 </struct>
 <struct from="5007" id="n02646241_wf2" to="5014" type="auto">
  <feat name="wnsk" value="sculpin%1:05:00::"/>
  <feat name="text" value="sculpin"/>
 </struct>
 <struct from="5022" id="n02646241_wf5" to="5027" type="man">
  <feat name="wnsk" value="coast%1:17:00::"/>
  <feat name="text" value="coast"/>
 </struct>
 <struct from="5044" id="n02646377_wf1" to="5054" type="auto">
  <feat name="wnsk" value="lumpfish%1:05:00::"/>
  <feat name="text" value="lumpfishes"/>
 </struct>
 <struct from="5074" id="n02646508_wf5" to="5087" type="auto">
  <feat name="wnsk" value="cyclopteridae%1:05:00::"/>
  <feat name="text" value="Cyclopteridae"/>
 </struct>
 <struct from="5089" id="n02646508_wf7" to="5099" type="auto">
  <feat name="wnsk" value="lumpfish%1:05:00::"/>
  <feat name="text" value="lumpfishes"/>
 </struct>
 <struct from="5101" id="n02646667_wf1" to="5107" type="man">
  <feat name="wnsk" value="clumsy%3:00:00:awkward:00"/>
  <feat name="text" value="clumsy"/>
 </struct>
 <struct from="5108" id="n02646667_wf2" to="5112" type="un">
  <feat name="text" value="soft"/>
 </struct>
 <struct from="5113" id="n02646667_wf3" to="5125" type="auto">
  <feat name="wnsk" value="thick-bodied%3:00:00:bodied:00"/>
  <feat name="text" value="thick-bodied"/>
 </struct>
 <struct from="5126" id="n02646667_wf4" to="5134" type="un">
  <feat name="text" value="northern"/>
 </struct>
 <struct from="5135" id="n02646667_wf5" to="5143" type="man">
  <feat name="wnsk" value="atlantic%3:01:00::"/>
  <feat name="text" value="Atlantic"/>
 </struct>
 <struct from="5144" id="n02646667_wf6" to="5148" type="man">
  <feat name="wnsk" value="fish%1:05:00::"/>
  <feat name="text" value="fish"/>
 </struct>
 <struct from="5166" id="n02646667_wf10" to="5171" type="man">
  <feat name="wnsk" value="fuse%2:30:00::"/>
  <feat name="text" value="fused"/>
 </struct>
 <struct from="5179" id="n02646667_wf13" to="5185" type="man">
  <feat name="wnsk" value="sucker%1:05:02::"/>
  <feat name="text" value="sucker"/>
 </struct>
 <struct from="5187" id="n02646667_wf15" to="5193" type="man">
  <feat name="wnsk" value="edible%3:00:00::"/>
  <feat name="text" value="edible"/>
 </struct>
 <struct from="5194" id="n02646667_wf16" to="5197" type="un">
  <feat name="text" value="roe"/>
 </struct>
 <struct from="5198" id="n02646667_wf17" to="5202" type="un">
  <feat name="text" value="used"/>
 </struct>
 <struct from="5207" id="n02646667_wf19" to="5213" type="auto">
  <feat name="wnsk" value="caviar%1:13:00::"/>
  <feat name="text" value="caviar"/>
 </struct>
 <struct from="5222" id="n02646892_wf3" to="5229" type="un">
  <feat name="text" value="several"/>
 </struct>
 <struct from="5230" id="n02646892_wf4" to="5234" type="un">
  <feat name="text" value="very"/>
 </struct>
 <struct from="5235" id="n02646892_wf5" to="5240" type="man">
  <feat name="wnsk" value="small%3:00:00::"/>
  <feat name="text" value="small"/>
 </struct>
 <struct from="5241" id="n02646892_wf6" to="5251" type="auto">
  <feat name="wnsk" value="lumpfish%1:05:00::"/>
  <feat name="text" value="lumpfishes"/>
 </struct>
 <struct from="5253" id="n02646985_wf1" to="5264" type="auto">
  <feat name="wnsk" value="snailfish%1:05:00::"/>
  <feat name="text" value="snailfishes"/>
 </struct>
 <struct from="5284" id="n02647144_wf5" to="5295" type="auto">
  <feat name="wnsk" value="liparididae%1:05:00::"/>
  <feat name="text" value="Liparididae"/>
 </struct>
 <struct from="5297" id="n02647144_wf7" to="5308" type="auto">
  <feat name="wnsk" value="snailfish%1:05:00::"/>
  <feat name="text" value="snailfishes"/>
 </struct>
</cesAna>
