<?xml version="1.0" encoding="UTF-8"?>
<cesAna version="1.0.4" xmlns="http://www.xces.org/schema/2003" xmlns:xlink="http://www.w3.org/1999/xlink" xmlns:xsi="http://www.w3.org/2001/XMLSchema-instance" xsi:schemaLocation="http://www.xces.org/schema/2003 http://www.xces.org/schema/2003/xcesAna.xsd">
 <struct from="0" id="n00787465_d" to="55" type="def"/>
 <struct from="56" id="n00787465_ex1" to="111" type="ex"/>
 <struct from="112" id="n00787465_ex2" to="149" type="ex"/>
 <struct from="150" id="n00787727_d" to="184" type="def"/>
 <struct from="185" id="n00787727_ex1" to="204" type="ex"/>
 <struct from="205" id="n00787832_d" to="251" type="def"/>
 <struct from="252" id="n00787832_ex1" to="286" type="ex"/>
 <struct from="287" id="n00788007_d" to="321" type="def"/>
 <struct from="322" id="n00788097_d" to="413" type="def"/>
 <struct from="414" id="n00788097_ex1" to="468" type="ex"/>
 <struct from="469" id="n00788362_d" to="509" type="def"/>
 <struct from="510" id="n00788473_d" to="551" type="def"/>
 <struct from="552" id="n00788473_ex1" to="577" type="ex"/>
 <struct from="578" id="n00788473_ex2" to="608" type="ex"/>
 <struct from="609" id="n00788632_d" to="639" type="def"/>
 <struct from="640" id="n00788766_d" to="678" type="def"/>
 <struct from="679" id="n00788973_d" to="721" type="def"/>
 <struct from="722" id="n00788973_ex1" to="768" type="ex"/>
 <struct from="769" id="n00788973_ex2" to="804" type="ex"/>
 <struct from="805" id="n00789237_d" to="873" type="def"/>
 <struct from="874" id="n00789391_d" to="917" type="def"/>
 <struct from="918" id="n00789534_d" to="995" type="def"/>
 <struct from="996" id="n00789735_d" to="1105" type="def"/>
 <struct from="1106" id="n00789906_d" to="1178" type="def"/>
 <struct from="1179" id="n00790086_d" to="1231" type="def"/>
 <struct from="1232" id="n00790205_d" to="1276" type="def"/>
 <struct from="1277" id="n00790347_d" to="1334" type="def"/>
 <struct from="1335" id="n00790498_d" to="1456" type="def"/>
 <struct from="1457" id="n00790677_d" to="1536" type="def"/>
 <struct from="1537" id="n00790817_d" to="1605" type="def"/>
 <struct from="1606" id="n00790947_d" to="1674" type="def"/>
 <struct from="1675" id="n00791078_d" to="1704" type="def"/>
 <struct from="1705" id="n00791078_ex1" to="1777" type="ex"/>
 <struct from="1778" id="n00791078_ex2" to="1822" type="ex"/>
 <struct from="1823" id="n00791527_d" to="2030" type="def"/>
 <struct from="2031" id="n00791875_d" to="2201" type="def"/>
 <struct from="2202" id="n00792142_d" to="2350" type="def"/>
 <struct from="2351" id="n00792356_d" to="2567" type="def"/>
 <struct from="2568" id="n00792720_d" to="2724" type="def"/>
 <struct from="2725" id="n00792954_d" to="2903" type="def"/>
 <struct from="2904" id="n00793212_d" to="3139" type="def"/>
 <struct from="3140" id="n00793529_d" to="3375" type="def"/>
 <struct from="3376" id="n00793844_d" to="3597" type="def"/>
 <struct from="3598" id="n00794123_d" to="3740" type="def"/>
 <struct from="3741" id="n00794367_d" to="3771" type="def"/>
 <struct from="3772" id="n00794367_ex1" to="3809" type="ex"/>
 <struct from="3810" id="n00794367_ex2" to="3854" type="ex"/>
 <struct from="3855" id="n00794614_d" to="3896" type="def"/>
 <struct from="3897" id="n00794772_d" to="3938" type="def"/>
 <struct from="3939" id="n00794870_d" to="4020" type="def"/>
 <struct from="4021" id="n00795008_d" to="4064" type="def"/>
 <struct from="4065" id="n00795161_d" to="4143" type="def"/>
 <struct from="4144" id="n00795352_d" to="4180" type="def"/>
 <struct from="4181" id="n00795352_ex1" to="4223" type="ex"/>
 <struct from="4224" id="n00795508_d" to="4286" type="def"/>
 <struct from="4287" id="n00795625_d" to="4328" type="def"/>
 <struct from="4329" id="n00795720_d" to="4379" type="def"/>
 <struct from="4380" id="n00795720_ex1" to="4415" type="ex"/>
 <struct from="4416" id="n00796197_d" to="4449" type="def"/>
 <struct from="4450" id="n00796315_d" to="4507" type="def"/>
 <struct from="4508" id="n00796586_d" to="4579" type="def"/>
 <struct from="4580" id="n00796767_d" to="4621" type="def"/>
 <struct from="4622" id="n00796767_ex1" to="4647" type="ex"/>
 <struct from="4648" id="n00796886_d" to="4738" type="def"/>
 <struct from="4739" id="n00796886_ex1" to="4780" type="ex"/>
 <struct from="4781" id="n00797207_d" to="4859" type="def"/>
 <struct from="4860" id="n00797361_d" to="4893" type="def"/>
 <struct from="4894" id="n00797468_d" to="4932" type="def"/>
 <struct from="4933" id="n00797581_d" to="4957" type="def"/>
 <struct from="4958" id="n00797581_ex1" to="5016" type="ex"/>
 <struct from="5017" id="n00797723_d" to="5050" type="def"/>
 <struct from="5051" id="n00797723_ex1" to="5100" type="ex"/>
 <struct from="5101" id="n00797878_d" to="5170" type="def"/>
 <struct from="5171" id="n00798108_d" to="5202" type="def"/>
 <struct from="5203" id="n00798245_d" to="5280" type="def"/>
 <struct from="5281" id="n00798245_ex1" to="5313" type="ex"/>
 <struct from="5314" id="n00798245_ex2" to="5354" type="ex"/>
 <struct from="5355" id="n00798245_ex3" to="5405" type="ex"/>
 <struct from="5406" id="n00798245_ex4" to="5434" type="ex"/>
 <struct from="5435" id="n00798245_ex5" to="5465" type="ex"/>
 <struct from="5466" id="n00798959_d" to="5505" type="def"/>
 <struct from="5506" id="n00799125_d" to="5554" type="def"/>
 <struct from="5555" id="n00799236_d" to="5668" type="def"/>
 <struct from="5669" id="n00799409_d" to="5740" type="def"/>
 <struct from="5741" id="n00799537_d" to="5783" type="def"/>
 <struct from="5784" id="n00799809_d" to="5853" type="def"/>
 <struct from="5854" id="n00799809_ex1" to="5935" type="ex"/>
 <struct from="5936" id="n00799809_ex2" to="6000" type="ex"/>
 <struct from="6001" id="n00800121_d" to="6077" type="def"/>
 <struct from="6078" id="n00800270_d" to="6119" type="def"/>
 <struct from="6120" id="n00800421_d" to="6165" type="def"/>
 <struct from="6166" id="n00800657_d" to="6255" type="def"/>
 <struct from="6256" id="n00800825_d" to="6315" type="def"/>
 <struct from="6316" id="n00800940_d" to="6367" type="def"/>
 <struct from="6368" id="n00800940_ex1" to="6429" type="ex"/>
 <struct from="6430" id="n00801125_d" to="6486" type="def"/>
 <struct from="6487" id="n00801125_ex1" to="6506" type="ex"/>
 <struct from="6507" id="n00801125_ex2" to="6529" type="ex"/>
 <struct from="6530" id="n00801277_d" to="6627" type="def"/>
 <struct from="6628" id="n00801450_d" to="6711" type="def"/>
 <struct from="6712" id="n00801598_d" to="6784" type="def"/>
 <struct from="6785" id="n00801724_d" to="6835" type="def"/>
 <struct from="6836" id="n00801834_d" to="6897" type="def"/>
 <struct from="6898" id="n00801966_d" to="6928" type="def"/>
 <struct from="6929" id="n00801966_ex1" to="6973" type="ex"/>
 <struct from="6974" id="n00802111_d" to="7046" type="def"/>
 <struct from="7047" id="n00802238_d" to="7110" type="def"/>
 <struct from="7111" id="n00802238_ex1" to="7157" type="ex"/>
 <struct from="7158" id="n00802238_ex2" to="7205" type="ex"/>
 <struct from="7206" id="n00802629_d" to="7230" type="def"/>
 <struct from="7231" id="n00802629_ex1" to="7272" type="ex"/>
 <struct from="7273" id="n00802785_d" to="7303" type="def"/>
 <struct from="7304" id="n00802785_ex1" to="7374" type="ex"/>
 <struct from="7375" id="n00802962_d" to="7398" type="def"/>
 <struct from="7399" id="n00803091_d" to="7461" type="def"/>
 <struct from="7462" id="n00803208_d" to="7505" type="def"/>
 <struct from="7506" id="n00803208_ex1" to="7540" type="ex"/>
 <struct from="7541" id="n00803394_d" to="7592" type="def"/>
 <struct from="7593" id="n00803394_ex1" to="7626" type="ex"/>
 <struct from="7627" id="n00803617_d" to="7687" type="def"/>
 <struct from="7688" id="n00803617_ex1" to="7739" type="ex"/>
 <struct from="7740" id="n00804180_d" to="7772" type="def"/>
 <struct from="7773" id="n00804271_d" to="7821" type="def"/>
 <struct from="7822" id="n00804379_d" to="7865" type="def"/>
 <struct from="7866" id="n00804535_d" to="7979" type="def"/>
 <struct from="7994" id="n00804708_d" to="8103" type="def"/>
 <struct from="8104" id="n00804909_d" to="8154" type="def"/>
 <struct from="8155" id="n00805034_d" to="8209" type="def"/>
 <struct from="8210" id="n00805034_ex1" to="8261" type="ex"/>
 <struct from="8262" id="n00805337_d" to="8340" type="def"/>
 <struct from="8341" id="n00805524_d" to="8472" type="def"/>
 <struct from="8473" id="n00805766_d" to="8518" type="def"/>
 <struct from="8519" id="n00805868_d" to="8652" type="def"/>
 <struct from="8653" id="n00806075_d" to="8809" type="def"/>
 <struct from="8810" id="n00806366_d" to="8864" type="def"/>
 <struct from="8865" id="n00806484_d" to="8923" type="def"/>
 <struct from="8924" id="n00806621_d" to="9122" type="def"/>
 <struct from="9123" id="n00806902_d" to="9173" type="def"/>
</cesAna>
